odoo8_addon_mail_full_expand-8.0.3.0.0.99.dev16-py2.7-nspkg.pth
odoo8_addon_mail_full_expand-8.0.3.0.0.99.dev16.dist-info/DESCRIPTION.rst
odoo8_addon_mail_full_expand-8.0.3.0.0.99.dev16.dist-info/METADATA
odoo8_addon_mail_full_expand-8.0.3.0.0.99.dev16.dist-info/RECORD
odoo8_addon_mail_full_expand-8.0.3.0.0.99.dev16.dist-info/WHEEL
odoo8_addon_mail_full_expand-8.0.3.0.0.99.dev16.dist-info/metadata.json
odoo8_addon_mail_full_expand-8.0.3.0.0.99.dev16.dist-info/namespace_packages.txt
odoo8_addon_mail_full_expand-8.0.3.0.0.99.dev16.dist-info/top_level.txt
odoo_addons/mail_full_expand/README.rst
odoo_addons/mail_full_expand/__init__.py
odoo_addons/mail_full_expand/__openerp__.py
odoo_addons/mail_full_expand/i18n/ca.po
odoo_addons/mail_full_expand/i18n/de.po
odoo_addons/mail_full_expand/i18n/el_GR.po
odoo_addons/mail_full_expand/i18n/es.po
odoo_addons/mail_full_expand/i18n/es_CO.po
odoo_addons/mail_full_expand/i18n/fi.po
odoo_addons/mail_full_expand/i18n/fr.po
odoo_addons/mail_full_expand/i18n/mail_full_expand.pot
odoo_addons/mail_full_expand/i18n/nb.po
odoo_addons/mail_full_expand/i18n/pt_BR.po
odoo_addons/mail_full_expand/i18n/sl.po
odoo_addons/mail_full_expand/static/description/icon.png
odoo_addons/mail_full_expand/static/src/css/mail_full_expand.css
odoo_addons/mail_full_expand/static/src/js/mail_full_expand.js
odoo_addons/mail_full_expand/static/src/xml/mail_full_expand.xml
odoo_addons/mail_full_expand/views/assets.xml
odoo_addons/mail_full_expand/views/mail_full_expand.xml
